lanctools/__init__.py
lanctools/_cpp.cpython-312-x86_64-linux-gnu.so
lanctools/cli.py
lanctools/core.py
lanctools/_cpp/bindings.cpp
lanctools/_cpp/flare.cpp
lanctools/_cpp/flare.hpp
lanctools/_cpp/rfmix.cpp
lanctools/_cpp/rfmix.hpp
lanctools-0.1.4.dist-info/METADATA
lanctools-0.1.4.dist-info/WHEEL
lanctools-0.1.4.dist-info/entry_points.txt
lanctools-0.1.4.dist-info/RECORD
lanctools-0.1.4.dist-info/licenses/LICENSE.txt
