Metadata-Version: 2.1
Name: lanctools
Version: 0.1.4
Summary: Tools for working with phased local ancestry data stored in the `.lanc` file format
Author-Email: Franklin Ockerman <frank.ockerman@gmail.com>
License: MIT
Project-URL: Homepage, https://github.com/frankp-0/lanctools
Project-URL: Repository, https://github.com/frankp-0/lanctools
Project-URL: Issues, https://github.com/frankp-0/lanctools/issues
Requires-Python: >=3.10
Requires-Dist: numba>=0.63.1
Requires-Dist: numpy>=2.2.6
Requires-Dist: pandas>=2.3.3
Requires-Dist: pgenlib>=0.93.0
Requires-Dist: typer>=0.20.1
